slurpit/__init__.py
slurpit/api.py
slurpit/apis/__init__.py
slurpit/apis/baseapi.py
slurpit/apis/deviceapi.py
slurpit/apis/planningapi.py
slurpit/apis/platformapi.py
slurpit/apis/scannerapi.py
slurpit/apis/scraperapi.py
slurpit/apis/siteapi.py
slurpit/apis/tagapi.py
slurpit/apis/templateapi.py
slurpit/apis/userapi.py
slurpit/apis/vaultapi.py
slurpit/config.py
slurpit/models/__init__.py
slurpit/models/basemodel.py
slurpit/models/device.py
slurpit/models/planning.py
slurpit/models/platform.py
slurpit/models/scanner.py
slurpit/models/site.py
slurpit/models/snmpcredential.py
slurpit/models/snmpgroup.py
slurpit/models/sshgroup.py
slurpit/models/tag.py
slurpit/models/template.py
slurpit/models/user.py
slurpit/models/vault.py
slurpit/utils/__init__.py
slurpit/utils/utils.py
slurpit_sdk-0.9.133.dist-info/METADATA
slurpit_sdk-0.9.133.dist-info/WHEEL
slurpit_sdk-0.9.133.dist-info/licenses/LICENSE
slurpit_sdk-0.9.133.dist-info/RECORD
