Metadata-Version: 2.4
Name: slurpit_sdk
Version: 0.9.133
Summary: A robust Python SDK for slurpit
License-File: LICENSE
Author: Slurp'it
Author-email: info@slurpit.io
Requires-Python: >=3.8
Classifier: Programming Language :: Python :: 3
Classifier: Programming Language :: Python :: 3.8
Classifier: Programming Language :: Python :: 3.9
Classifier: Programming Language :: Python :: 3.10
Classifier: Programming Language :: Python :: 3.11
Classifier: Programming Language :: Python :: 3.12
Classifier: Programming Language :: Python :: 3.13
Classifier: Programming Language :: Python :: 3.14
Provides-Extra: pandas
Requires-Dist: httpx (>=0.27.0,<0.28.0)
Requires-Dist: pandas (>=2.2.2,<3.0.0) ; (python_version >= "3.9") and (extra == "pandas")
Requires-Dist: python-dotenv (>=1.0.0,<2.0.0)
Requires-Dist: python-toon
